setup.py
hello_folder/SaludoLibrary.py
hello_folder/__init__.py
hello_folder.egg-info/PKG-INFO
hello_folder.egg-info/SOURCES.txt
hello_folder.egg-info/dependency_links.txt
hello_folder.egg-info/top_level.txt