Metadata-Version: 2.1
Name: hello-folder
Version: 0.0.1
Summary: Librería de prueba
Home-page: UNKNOWN
Author: Luis Francisco Gutierrez
Author-email: luis.gutierrez@zentagroup.com
License: MIT
Platform: UNKNOWN
